gpoanalyzer2/cli.py
gpoanalyzer2/py.typed
gpoanalyzer2-0.0.0.dist-info/METADATA
gpoanalyzer2-0.0.0.dist-info/WHEEL
gpoanalyzer2-0.0.0.dist-info/RECORD
