Metadata-Version: 2.4
Name: gpoanalyzer2
Version: 0.0.0
Summary: Placholder for futur use. Contact author if you really want to use this name
License-Expression: MIT
Author: wbi
Author-email: william.billaud@orange.com
Requires-Python: <4.0,>=3.12
Classifier: Programming Language :: Python :: 3
Classifier: Programming Language :: Python :: 3.12
Classifier: Programming Language :: Python :: 3.13
Classifier: Programming Language :: Python :: 3.14
